py_open_dsse/__init__.py
py_open_dsse/Algorithm_classification.py
py_open_dsse/base_DSSE.py
py_open_dsse/DSSE_algorithms/__init__.py
py_open_dsse/DSSE_algorithms/Symb_Eqn/__init__.py
py_open_dsse/DSSE_algorithms/Symb_Eqn/sym_func_1ph.py
py_open_dsse/DSSE_algorithms/Symb_Eqn/sym_func_Pos_Seq.py
py_open_dsse/DSSE_algorithms/WLS_alg_1ph.py
py_open_dsse/DSSE_algorithms/WLS_alg_Pos_Seq.py
py_open_dsse/Elec_param_calc_DSS_EST.py
py_open_dsse/error_handling_logging.py
py_open_dsse/examples/13NodeIEEE/MEAS_files/Init_Bus_i.json
py_open_dsse/examples/13NodeIEEE/MEAS_files/Init_Bus_i_PMU.json
py_open_dsse/examples/13NodeIEEE/MEAS_files/Init_Elem_ft.json
py_open_dsse/examples/13NodeIEEE/MEAS_files/Init_Elem_ft_PMU.json
py_open_dsse/examples/13NodeIEEE/MEAS_files/MEAS_Bus_i.json
py_open_dsse/examples/13NodeIEEE/MEAS_files/MEAS_Bus_i_PMU.json
py_open_dsse/examples/13NodeIEEE/MEAS_files/MEAS_Elem_ft.json
py_open_dsse/examples/13NodeIEEE/MEAS_files/MEAS_Elem_ft_PMU.json
py_open_dsse/examples/13NodeIEEE/MEAS_files/Pos_MEAS_Bus_i.json
py_open_dsse/examples/13NodeIEEE/MEAS_files/Pos_MEAS_Bus_i_PMU.json
py_open_dsse/examples/13NodeIEEE/MEAS_files/Pos_MEAS_Elem_ft.json
py_open_dsse/examples/13NodeIEEE/MEAS_files/Pos_MEAS_Elem_ft_PMU.json
py_open_dsse/examples/13NodeIEEE/OpenDSS files/Capacitors.DSS
py_open_dsse/examples/13NodeIEEE/OpenDSS files/IEEE13Node_BusXY.csv
py_open_dsse/examples/13NodeIEEE/OpenDSS files/IEEE13Nodeckt_Power.DSV
py_open_dsse/examples/13NodeIEEE/OpenDSS files/IEEELineCodes.DSS
py_open_dsse/examples/13NodeIEEE/OpenDSS files/LineCodes.dss
py_open_dsse/examples/13NodeIEEE/OpenDSS files/Lines.DSS
py_open_dsse/examples/13NodeIEEE/OpenDSS files/Loads.DSS
py_open_dsse/examples/13NodeIEEE/OpenDSS files/Master13NodeIEEE.dss
py_open_dsse/examples/13NodeIEEE/OpenDSS files/PosSeq circuit/BusCoords.dss
py_open_dsse/examples/13NodeIEEE/OpenDSS files/PosSeq circuit/BusVoltageBases.DSS
py_open_dsse/examples/13NodeIEEE/OpenDSS files/PosSeq circuit/Capacitor.DSS
py_open_dsse-0.1.1.dist-info/LICENSE.md
py_open_dsse-0.1.1.dist-info/WHEEL
py_open_dsse-0.1.1.dist-info/METADATA
py_open_dsse-0.1.1.dist-info/RECORD
